{"141 00":["SE","141 00","Huddinge","Stockholm","AB","Huddinge","0126","","","59.237","17.9819","4"],"141 01":["SE","141 01","Huddinge","Stockholm","AB","Huddinge","0126","","","59.237","17.9819","4"],"141 02":["SE","141 02","Huddinge","Stockholm","AB","Huddinge","0126","","","59.237","17.9819","4"],"141 04":["SE","141 04","Huddinge","Stockholm","AB","Huddinge","0126","","","59.237","17.9819","4"],"141 05":["SE","141 05","Huddinge","Stockholm","AB","Huddinge","0126","","","59.237","17.9819","4"],"141 06":["SE","141 06","Kungens Kurva","Stockholm","AB","Huddinge","0126","","","59.237","17.9819","1"],"141 07":["SE","141 07","Huddinge","Stockholm","AB","Huddinge","0126","","","59.237","17.9819","4"],"141 08":["SE","141 08","Kungens Kurva","Stockholm","AB","Huddinge","0126","","","59.237","17.9819",""],"141 09":["SE","141 09","Huddinge","Stockholm","AB","Huddinge","0126","","","59.237","17.9819","4"],"141 12":["SE","141 12","Huddinge","Stockholm","AB","Huddinge","0126","","","59.237","17.9819","4"],"141 18":["SE","141 18","Huddinge","Stockholm","AB","Huddinge","0126","","","59.237","17.9819","4"],"141 21":["SE","141 21","Huddinge","Stockholm","AB","Huddinge","0126","","","59.237","17.9819","4"],"141 22":["SE","141 22","Huddinge","Stockholm","AB","Huddinge","0126","","","59.237","17.9819","4"],"141 23":["SE","141 23","Huddinge","Stockholm","AB","Huddinge","0126","","","59.237","17.9819","4"],"141 24":["SE","141 24","Huddinge","Stockholm","AB","Huddinge","0126","","","59.237","17.9819","4"],"141 25":["SE","141 25","Huddinge","Stockholm","AB","Huddinge","0126","","","59.237","17.9819","4"],"141 26":["SE","141 26","Huddinge","Stockholm","AB","Huddinge","0126","","","59.237","17.9819","4"],"141 27":["SE","141 27","Huddinge","Stockholm","AB","Huddinge","0126","","","59.237","17.9819","4"],"141 28":["SE","141 28","Huddinge","Stockholm","AB","Huddinge","0126","","","59.237","17.9819","4"],"141 30":["SE","141 30","Huddinge","Stockholm","AB","Huddinge","0126","","","59.237","17.9819","4"],"141 31":["SE","141 31","Huddinge","Stockholm","AB","Huddinge","0126","","","59.237","17.9819","4"],"141 32":["SE","141 32","Huddinge","Stockholm","AB","Huddinge","0126","","","59.237","17.9819","4"],"141 33":["SE","141 33","Huddinge","Stockholm","AB","Huddinge","0126","","","59.237","17.9819","4"],"141 34":["SE","141 34","Huddinge","Stockholm","AB","Huddinge","0126","","","59.237","17.9819","4"],"141 35":["SE","141 35","Huddinge","Stockholm","AB","Huddinge","0126","","","59.237","17.9819","4"],"141 37":["SE","141 37","Huddinge","Stockholm","AB","Huddinge","0126","","","59.237","17.9819","4"],"141 38":["SE","141 38","Huddinge","Stockholm","AB","Huddinge","0126","","","59.237","17.9819","4"],"141 39":["SE","141 39","Huddinge","Stockholm","AB","Huddinge","0126","","","59.237","17.9819","4"],"141 40":["SE","141 40","Huddinge","Stockholm","AB","Huddinge","0126","","","59.237","17.9819","4"],"141 41":["SE","141 41","Huddinge","Stockholm","AB","Huddinge","0126","","","59.237","17.9819","4"],"141 42":["SE","141 42","Huddinge","Stockholm","AB","Huddinge","0126","","","59.237","17.9819","4"],"141 43":["SE","141 43","Huddinge","Stockholm","AB","Huddinge","0126","","","59.237","17.9819","4"],"141 44":["SE","141 44","Huddinge","Stockholm","AB","Huddinge","0126","","","59.237","17.9819","4"],"141 45":["SE","141 45","Huddinge","Stockholm","AB","Huddinge","0126","","","59.237","17.9819","4"],"141 46":["SE","141 46","Huddinge","Stockholm","AB","Huddinge","0126","","","59.237","17.9819","4"],"141 47":["SE","141 47","Huddinge","Stockholm","AB","Huddinge","0126","","","59.237","17.9819","4"],"141 48":["SE","141 48","Huddinge","Stockholm","AB","Huddinge","0126","","","59.237","17.9819","4"],"141 49":["SE","141 49","Huddinge","Stockholm","AB","Huddinge","0126","","","59.237","17.9819","4"],"141 50":["SE","141 50","Huddinge","Stockholm","AB","Huddinge","0126","","","59.237","17.9819","4"],"141 51":["SE","141 51","Huddinge","Stockholm","AB","Huddinge","0126","","","59.237","17.9819","4"],"141 52":["SE","141 52","Huddinge","Stockholm","AB","Huddinge","0126","","","59.237","17.9819","4"],"141 53":["SE","141 53","Huddinge","Stockholm","AB","Huddinge","0126","","","59.237","17.9819","4"],"141 54":["SE","141 54","Huddinge","Stockholm","AB","Huddinge","0126","","","59.237","17.9819","4"],"141 55":["SE","141 55","Huddinge","Stockholm","AB","Huddinge","0126","","","59.237","17.9819","4"],"141 56":["SE","141 56","Huddinge","Stockholm","AB","Huddinge","0126","","","59.237","17.9819","4"],"141 57":["SE","141 57","Huddinge","Stockholm","AB","Huddinge","0126","","","59.237","17.9819","4"],"141 59":["SE","141 59","Huddinge","Stockholm","AB","Huddinge","0126","","","59.237","17.9819","4"],"141 60":["SE","141 60","Huddinge","Stockholm","AB","Huddinge","0126","","","59.237","17.9819","4"],"141 61":["SE","141 61","Huddinge","Stockholm","AB","Huddinge","0126","","","59.237","17.9819","4"],"141 62":["SE","141 62","Huddinge","Stockholm","AB","Huddinge","0126","","","59.237","17.9819","4"],"141 70":["SE","141 70","Segeltorp","Stockholm","AB","Huddinge","0126","","","59.2833","17.9333","4"],"141 71":["SE","141 71","Segeltorp","Stockholm","AB","Huddinge","0126","","","59.2833","17.9333","4"],"141 72":["SE","141 72","Segeltorp","Stockholm","AB","Huddinge","0126","","","59.2833","17.9333","4"],"141 73":["SE","141 73","Segeltorp","Stockholm","AB","Huddinge","0126","","","59.2833","17.9333","4"],"141 75":["SE","141 75","Kungens Kurva","Stockholm","AB","Huddinge","0126","","","59.2833","17.9333","1"],"141 81":["SE","141 81","Huddinge","Stockholm","AB","Huddinge","0126","","","59.237","17.9819","4"],"141 83":["SE","141 83","Huddinge","Stockholm","AB","Huddinge","0126","","","59.237","17.9819","4"],"141 84":["SE","141 84","Huddinge","Stockholm","AB","Huddinge","0126","","","59.237","17.9819","4"],"141 85":["SE","141 85","Huddinge","Stockholm","AB","Huddinge","0126","","","59.237","17.9819","4"],"141 87":["SE","141 87","Huddinge","Stockholm","AB","Huddinge","0126","","","59.237","17.9819","4"],"141 88":["SE","141 88","Huddinge","Stockholm","AB","Huddinge","0126","","","59.237","17.9819","4"],"141 89":["SE","141 89","Huddinge","Stockholm","AB","Huddinge","0126","","","59.237","17.9819","4"],"141 91":["SE","141 91","Huddinge","Stockholm","AB","Huddinge","0126","","","59.237","17.9819","4"],"142 00":["SE","142 00","Skog\u00e5s","Stockholm","AB","Huddinge","0126","","","59.2167","18.15","4"],"142 02":["SE","142 02","Tr\u00e5ngsund","Stockholm","AB","Huddinge","0126","","","59.2333","18.1333","4"],"142 21":["SE","142 21","Skog\u00e5s","Stockholm","AB","Huddinge","0126","","","59.2167","18.15","4"],"142 22":["SE","142 22","Skog\u00e5s","Stockholm","AB","Huddinge","0126","","","59.2167","18.15","4"],"142 25":["SE","142 25","Skog\u00e5s","Stockholm","AB","Huddinge","0126","","","59.2167","18.15","4"],"142 29":["SE","142 29","Tr\u00e5ngsund","Stockholm","AB","Huddinge","0126","","","59.2333","18.1333","4"],"142 30":["SE","142 30","Skog\u00e5s","Stockholm","AB","Huddinge","0126","","","59.2167","18.15","4"],"142 31":["SE","142 31","Skog\u00e5s","Stockholm","AB","Huddinge","0126","","","59.2167","18.15","4"],"142 32":["SE","142 32","Skog\u00e5s","Stockholm","AB","Huddinge","0126","","","59.2167","18.15","4"],"142 33":["SE","142 33","Skog\u00e5s","Stockholm","AB","Huddinge","0126","","","59.2167","18.15","4"],"142 34":["SE","142 34","Skog\u00e5s","Stockholm","AB","Huddinge","0126","","","59.2167","18.15","4"],"142 35":["SE","142 35","Skog\u00e5s","Stockholm","AB","Huddinge","0126","","","59.2167","18.15","4"],"142 40":["SE","142 40","Skog\u00e5s","Stockholm","AB","Huddinge","0126","","","59.2167","18.15","4"],"142 41":["SE","142 41","Skog\u00e5s","Stockholm","AB","Huddinge","0126","","","59.2167","18.15","4"],"142 42":["SE","142 42","Skog\u00e5s","Stockholm","AB","Huddinge","0126","","","59.2167","18.15","4"],"142 43":["SE","142 43","Skog\u00e5s","Stockholm","AB","Huddinge","0126","","","59.2167","18.15","4"],"142 50":["SE","142 50","Skog\u00e5s","Stockholm","AB","Huddinge","0126","","","59.2167","18.15","4"],"142 51":["SE","142 51","Skog\u00e5s","Stockholm","AB","Huddinge","0126","","","59.2167","18.15","4"],"142 52":["SE","142 52","Skog\u00e5s","Stockholm","AB","Huddinge","0126","","","59.2167","18.15","4"],"142 53":["SE","142 53","Skog\u00e5s","Stockholm","AB","Huddinge","0126","","","59.2167","18.15","4"],"142 60":["SE","142 60","Tr\u00e5ngsund","Stockholm","AB","Huddinge","0126","","","59.2333","18.1333","4"],"142 61":["SE","142 61","Tr\u00e5ngsund","Stockholm","AB","Huddinge","0126","","","59.2333","18.1333","4"],"142 62":["SE","142 62","Tr\u00e5ngsund","Stockholm","AB","Huddinge","0126","","","59.2333","18.1333","4"],"142 63":["SE","142 63","Tr\u00e5ngsund","Stockholm","AB","Huddinge","0126","","","59.2333","18.1333","4"],"142 64":["SE","142 64","Tr\u00e5ngsund","Stockholm","AB","Huddinge","0126","","","59.2333","18.1333","4"],"142 65":["SE","142 65","Tr\u00e5ngsund","Stockholm","AB","Huddinge","0126","","","59.2333","18.1333","4"],"142 66":["SE","142 66","Tr\u00e5ngsund","Stockholm","AB","Huddinge","0126","","","59.2333","18.1333","4"],"142 81":["SE","142 81","Skog\u00e5s","Stockholm","AB","Huddinge","0126","","","59.2167","18.15","4"],"142 82":["SE","142 82","Tr\u00e5ngsund","Stockholm","AB","Huddinge","0126","","","59.2333","18.1333","4"],"142 91":["SE","142 91","Skog\u00e5s","Stockholm","AB","Huddinge","0126","","","59.2167","18.15","4"],"143 00":["SE","143 00","V\u00e5rby","Stockholm","AB","Huddinge","0126","","","59.2667","17.8833","4"],"143 01":["SE","143 01","V\u00e5rby","Stockholm","AB","Huddinge","0126","","","59.2667","17.8833","4"],"143 03":["SE","143 03","V\u00e5rby","Stockholm","AB","Huddinge","0126","","","59.2667","17.8833","4"],"143 30":["SE","143 30","V\u00e5rby","Stockholm","AB","Huddinge","0126","","","59.2667","17.8833","4"],"143 31":["SE","143 31","V\u00e5rby","Stockholm","AB","Huddinge","0126","","","59.2667","17.8833","4"],"143 32":["SE","143 32","V\u00e5rby","Stockholm","AB","Huddinge","0126","","","59.2667","17.8833","4"],"143 35":["SE","143 35","V\u00e5rby","Stockholm","AB","Huddinge","0126","","","59.2667","17.8833","4"],"143 40":["SE","143 40","V\u00e5rby","Stockholm","AB","Huddinge","0126","","","59.2667","17.8833","4"],"143 41":["SE","143 41","V\u00e5rby","Stockholm","AB","Huddinge","0126","","","59.2667","17.8833","4"],"143 42":["SE","143 42","V\u00e5rby","Stockholm","AB","Huddinge","0126","","","59.2667","17.8833","4"],"143 43":["SE","143 43","V\u00e5rby","Stockholm","AB","Huddinge","0126","","","59.2667","17.8833","4"],"143 44":["SE","143 44","V\u00e5rby","Stockholm","AB","Huddinge","0126","","","59.2667","17.8833","4"],"143 45":["SE","143 45","V\u00e5rby","Stockholm","AB","Huddinge","0126","","","59.2667","17.8833","4"],"143 47":["SE","143 47","V\u00e5rby","Stockholm","AB","Huddinge","0126","","","59.2667","17.8833","4"],"145 00":["SE","145 00","Norsborg","Stockholm","AB","Botkyrka","0127","","","59.25","17.7833","4"],"145 01":["SE","145 01","Norsborg","Stockholm","AB","Botkyrka","0127","","","59.25","17.7833","4"],"145 02":["SE","145 02","Norsborg","Stockholm","AB","Botkyrka","0127","","","59.25","17.7833","4"],"145 03":["SE","145 03","Norsborg","Stockholm","AB","Botkyrka","0127","","","59.25","17.7833","4"],"145 04":["SE","145 04","Norsborg","Stockholm","AB","Botkyrka","0127","","","59.25","17.7833","4"],"145 50":["SE","145 50","Norsborg","Stockholm","AB","Botkyrka","0127","","","59.25","17.7833","4"],"145 51":["SE","145 51","Norsborg","Stockholm","AB","Botkyrka","0127","","","59.25","17.7833","4"],"145 52":["SE","145 52","Norsborg","Stockholm","AB","Botkyrka","0127","","","59.25","17.7833","4"],"145 53":["SE","145 53","Norsborg","Stockholm","AB","Botkyrka","0127","","","59.25","17.7833","4"],"145 56":["SE","145 56","Norsborg","Stockholm","AB","Botkyrka","0127","","","59.25","17.7833","4"],"145 57":["SE","145 57","Norsborg","Stockholm","AB","Botkyrka","0127","","","59.25","17.7833","4"],"145 58":["SE","145 58","Norsborg","Stockholm","AB","Botkyrka","0127","","","59.25","17.7833","4"],"145 59":["SE","145 59","Norsborg","Stockholm","AB","Botkyrka","0127","","","59.25","17.7833","4"],"145 60":["SE","145 60","Norsborg","Stockholm","AB","Botkyrka","0127","","","59.25","17.7833","4"],"145 63":["SE","145 63","Norsborg","Stockholm","AB","Botkyrka","0127","","","59.25","17.7833","4"],"145 64":["SE","145 64","Norsborg","Stockholm","AB","Botkyrka","0127","","","59.25","17.7833","4"],"145 65":["SE","145 65","Norsborg","Stockholm","AB","Botkyrka","0127","","","59.25","17.7833","4"],"145 67":["SE","145 67","Norsborg","Stockholm","AB","Botkyrka","0127","","","59.25","17.7833","4"],"145 68":["SE","145 68","Norsborg","Stockholm","AB","Botkyrka","0127","","","59.25","17.7833","4"],"145 69":["SE","145 69","Norsborg","Stockholm","AB","Botkyrka","0127","","","59.25","17.7833","4"],"145 70":["SE","145 70","Norsborg","Stockholm","AB","Botkyrka","0127","","","59.25","17.7833","4"],"145 71":["SE","145 71","Norsborg","Stockholm","AB","Botkyrka","0127","","","59.25","17.7833","4"],"145 72":["SE","145 72","Norsborg","Stockholm","AB","Botkyrka","0127","","","59.25","17.7833","4"],"145 73":["SE","145 73","Norsborg","Stockholm","AB","Botkyrka","0127","","","59.25","17.7833","4"],"145 74":["SE","145 74","Norsborg","Stockholm","AB","Botkyrka","0127","","","59.25","17.7833","4"],"145 81":["SE","145 81","Norsborg","Stockholm","AB","Botkyrka","0127","","","59.25","17.7833","4"],"145 83":["SE","145 83","Norsborg","Stockholm","AB","Botkyrka","0127","","","59.25","17.7833","4"],"145 88":["SE","145 88","Norsborg","Stockholm","AB","Botkyrka","0127","","","59.25","17.7833","4"],"145 90":["SE","145 90","Norsborg","Stockholm","AB","Botkyrka","0127","","","59.25","17.7833","4"],"146 00":["SE","146 00","Tullinge","Stockholm","AB","Botkyrka","0127","","","59.2","17.8833","4"],"146 21":["SE","146 21","Tullinge","Stockholm","AB","Botkyrka","0127","","","59.2","17.8833","4"],"146 22":["SE","146 22","Tullinge","Stockholm","AB","Botkyrka","0127","","","59.2","17.8833","4"],"146 30":["SE","146 30","Tullinge","Stockholm","AB","Botkyrka","0127","","","59.2","17.8833","4"],"146 31":["SE","146 31","Tullinge","Stockholm","AB","Botkyrka","0127","","","59.2","17.8833","4"],"146 32":["SE","146 32","Tullinge","Stockholm","AB","Botkyrka","0127","","","59.2","17.8833","4"],"146 33":["SE","146 33","Tullinge","Stockholm","AB","Botkyrka","0127","","","59.2","17.8833","4"],"146 36":["SE","146 36","Tullinge","Stockholm","AB","Botkyrka","0127","","","59.2","17.8833","4"],"146 37":["SE","146 37","Tullinge","Stockholm","AB","Botkyrka","0127","","","59.2","17.8833","4"],"146 38":["SE","146 38","Tullinge","Stockholm","AB","Botkyrka","0127","","","59.2","17.8833","4"],"146 40":["SE","146 40","Tullinge","Stockholm","AB","Botkyrka","0127","","","59.2","17.8833","4"],"146 41":["SE","146 41","Tullinge","Stockholm","AB","Botkyrka","0127","","","59.2","17.8833","4"],"146 45":["SE","146 45","Tullinge","Stockholm","AB","Botkyrka","0127","","","59.2","17.8833","4"],"146 46":["SE","146 46","Tullinge","Stockholm","AB","Botkyrka","0127","","","59.2","17.8833","4"],"146 48":["SE","146 48","Tullinge","Stockholm","AB","Botkyrka","0127","","","59.2","17.8833","4"],"146 49":["SE","146 49","Tullinge","Stockholm","AB","Botkyrka","0127","","","59.2","17.8833","4"],"146 50":["SE","146 50","Tullinge","Stockholm","AB","Botkyrka","0127","","","59.2","17.8833","4"],"146 52":["SE","146 52","Tullinge","Stockholm","AB","Botkyrka","0127","","","59.2","17.8833","4"],"146 53":["SE","146 53","Tullinge","Stockholm","AB","Botkyrka","0127","","","59.2","17.8833","4"],"146 54":["SE","146 54","Tullinge","Stockholm","AB","Botkyrka","0127","","","59.2","17.8833","4"],"146 80":["SE","146 80","Tullinge","Stockholm","AB","Botkyrka","0127","","","59.2","17.8833","4"],"147 00":["SE","147 00","Tumba","Stockholm","AB","Botkyrka","0127","","","59.1986","17.8332","4"],"147 01":["SE","147 01","Tumba","Stockholm","AB","Botkyrka","0127","","","59.1986","17.8332","4"],"147 07":["SE","147 07","Gr\u00f6dinge","Stockholm","AB","Botkyrka","0127","","","59.1986","17.8332","1"],"147 21":["SE","147 21","Tumba","Stockholm","AB","Botkyrka","0127","","","59.1986","17.8332","4"],"147 22":["SE","147 22","Tumba","Stockholm","AB","Botkyrka","0127","","","59.1986","17.8332","4"],"147 23":["SE","147 23","Tumba","Stockholm","AB","Botkyrka","0127","","","59.1986","17.8332","4"],"147 25":["SE","147 25","Tumba","Stockholm","AB","Botkyrka","0127","","","59.1986","17.8332","4"],"147 30":["SE","147 30","Tumba","Stockholm","AB","Botkyrka","0127","","","59.1986","17.8332","4"],"147 31":["SE","147 31","Tumba","Stockholm","AB","Botkyrka","0127","","","59.1986","17.8332","4"],"147 32":["SE","147 32","Tumba","Stockholm","AB","Botkyrka","0127","","","59.1986","17.8332","4"],"147 33":["SE","147 33","Tumba","Stockholm","AB","Botkyrka","0127","","","59.1986","17.8332","4"],"147 34":["SE","147 34","Tumba","Stockholm","AB","Botkyrka","0127","","","59.1986","17.8332","4"],"147 39":["SE","147 39","Tumba","Stockholm","AB","Botkyrka","0127","","","59.1986","17.8332","4"],"147 40":["SE","147 40","Tumba","Stockholm","AB","Botkyrka","0127","","","59.1986","17.8332","4"],"147 41":["SE","147 41","Tumba","Stockholm","AB","Botkyrka","0127","","","59.1986","17.8332","4"],"147 42":["SE","147 42","Tumba","Stockholm","AB","Botkyrka","0127","","","59.1986","17.8332","4"],"147 43":["SE","147 43","Tumba","Stockholm","AB","Botkyrka","0127","","","59.1986","17.8332","4"],"147 44":["SE","147 44","Tumba","Stockholm","AB","Botkyrka","0127","","","59.1986","17.8332","4"],"147 50":["SE","147 50","Tumba","Stockholm","AB","Botkyrka","0127","","","59.1986","17.8332","4"],"147 51":["SE","147 51","Tumba","Stockholm","AB","Botkyrka","0127","","","59.1986","17.8332","4"],"147 52":["SE","147 52","Tumba","Stockholm","AB","Botkyrka","0127","","","59.1986","17.8332","4"],"147 53":["SE","147 53","Tumba","Stockholm","AB","Botkyrka","0127","","","59.1986","17.8332","4"],"147 54":["SE","147 54","Tumba","Stockholm","AB","Botkyrka","0127","","","59.1986","17.8332","4"],"147 55":["SE","147 55","Tumba","Stockholm","AB","Botkyrka","0127","","","59.1986","17.8332","4"],"147 60":["SE","147 60","Uttran","Stockholm","AB","Botkyrka","0127","","","59.2","17.8","4"],"147 61":["SE","147 61","Uttran","Stockholm","AB","Botkyrka","0127","","","59.2","17.8","4"],"147 62":["SE","147 62","Uttran","Stockholm","AB","Botkyrka","0127","","","59.2","17.8","4"],"147 63":["SE","147 63","Uttran","Stockholm","AB","Botkyrka","0127","","","59.2","17.8","4"],"147 70":["SE","147 70","Gr\u00f6dinge","Stockholm","AB","Botkyrka","0127","","","59.1988","17.829","1"],"147 71":["SE","147 71","Gr\u00f6dinge","Stockholm","AB","Botkyrka","0127","","","59.1988","17.829","1"],"147 80":["SE","147 80","Tumba","Stockholm","AB","Botkyrka","0127","","","59.1986","17.8332","4"],"147 82":["SE","147 82","Tumba","Stockholm","AB","Botkyrka","0127","","","59.1986","17.8332","4"],"147 85":["SE","147 85","Tumba","Stockholm","AB","Botkyrka","0127","","","59.1986","17.8332","4"],"147 92":["SE","147 92","Gr\u00f6dinge","Stockholm","AB","Botkyrka","0127","","","59.1988","17.829","1"],"144 00":["SE","144 00","R\u00f6nninge","Stockholm","AB","Salem","0128","","","59.2","17.7333","4"],"144 02":["SE","144 02","R\u00f6nninge","Stockholm","AB","Salem","0128","","","59.2","17.7333","4"],"144 21":["SE","144 21","R\u00f6nninge","Stockholm","AB","Salem","0128","","","59.2","17.7333","4"],"144 24":["SE","144 24","R\u00f6nninge","Stockholm","AB","Salem","0128","","","59.2","17.7333","4"],"144 30":["SE","144 30","R\u00f6nninge","Stockholm","AB","Salem","0128","","","59.2","17.7333","4"],"144 31":["SE","144 31","R\u00f6nninge","Stockholm","AB","Salem","0128","","","59.2","17.7333","4"],"144 32":["SE","144 32","R\u00f6nninge","Stockholm","AB","Salem","0128","","","59.2","17.7333","4"],"144 33":["SE","144 33","R\u00f6nninge","Stockholm","AB","Salem","0128","","","59.2","17.7333","4"],"144 37":["SE","144 37","R\u00f6nninge","Stockholm","AB","Salem","0128","","","59.2","17.7333","4"],"144 40":["SE","144 40","R\u00f6nninge","Stockholm","AB","Salem","0128","","","59.2","17.7333","4"],"144 42":["SE","144 42","R\u00f6nninge","Stockholm","AB","Salem","0128","","","59.2","17.7333","4"],"144 44":["SE","144 44","R\u00f6nninge","Stockholm","AB","Salem","0128","","","59.2","17.7333","4"],"144 51":["SE","144 51","R\u00f6nninge","Stockholm","AB","Salem","0128","","","59.2","17.7333","4"],"144 61":["SE","144 61","R\u00f6nninge","Stockholm","AB","Salem","0128","","","59.2","17.7333","4"],"144 62":["SE","144 62","R\u00f6nninge","Stockholm","AB","Salem","0128","","","59.2","17.7333","4"],"144 63":["SE","144 63","R\u00f6nninge","Stockholm","AB","Salem","0128","","","59.2","17.7333","4"],"144 64":["SE","144 64","R\u00f6nninge","Stockholm","AB","Salem","0128","","","59.2","17.7333","4"],"144 80":["SE","144 80","R\u00f6nninge","Stockholm","AB","Salem","0128","","","59.2","17.7333","4"],"148 25":["SE","148 25","Musk\u00f6","Stockholm","AB","Haninge","0136","","","58.9831","18.1331","4"],"148 80":["SE","148 80","Musk\u00f6","Stockholm","AB","Haninge","0136","","","58.9831","18.1331","4"],"148 95":["SE","148 95","Musk\u00f6","Stockholm","AB","Haninge","0136","","","58.9831","18.1331","4"],"141 82":["SE","141 82","Stockholm","Stockholm","AB","Stockholm","0180","","","59.3326","18.0649","4"],"141 86":["SE","141 86","Stockholm","Stockholm","AB","Stockholm","0180","","","59.3326","18.0649","4"],"141 99":["SE","141 99","Stockholm","Stockholm","AB","Stockholm","0180","","","59.3326","18.0649","4"],"143 46":["SE","143 46","V\u00e5rby","Stockholm","AB","Stockholm","0180","","","59.2667","17.8833","4"],"145 84":["SE","145 84","Stockholm","Stockholm","AB","Stockholm","0180","","","59.3326","18.0649","4"],"147 91":["SE","147 91","Gr\u00f6dinge","Stockholm","AB","Nyn\u00e4shamn","0192","","","59.1988","17.829","1"],"148 00":["SE","148 00","\u00d6smo","Stockholm","AB","Nyn\u00e4shamn","0192","","","58.9833","17.9","4"],"148 02":["SE","148 02","Sorunda","Stockholm","AB","Nyn\u00e4shamn","0192","","","58.9833","17.9","1"],"148 21":["SE","148 21","\u00d6smo","Stockholm","AB","Nyn\u00e4shamn","0192","","","58.9833","17.9","4"],"148 22":["SE","148 22","\u00d6smo","Stockholm","AB","Nyn\u00e4shamn","0192","","","58.9833","17.9","4"],"148 30":["SE","148 30","\u00d6smo","Stockholm","AB","Nyn\u00e4shamn","0192","","","58.9833","17.9","4"],"148 31":["SE","148 31","\u00d6smo","Stockholm","AB","Nyn\u00e4shamn","0192","","","58.9833","17.9","4"],"148 32":["SE","148 32","\u00d6smo","Stockholm","AB","Nyn\u00e4shamn","0192","","","58.9833","17.9","4"],"148 33":["SE","148 33","\u00d6smo","Stockholm","AB","Nyn\u00e4shamn","0192","","","58.9833","17.9","4"],"148 34":["SE","148 34","\u00d6smo","Stockholm","AB","Nyn\u00e4shamn","0192","","","58.9833","17.9","4"],"148 35":["SE","148 35","\u00d6smo","Stockholm","AB","Nyn\u00e4shamn","0192","","","58.9833","17.9","4"],"148 60":["SE","148 60","Stora Vika","Stockholm","AB","Nyn\u00e4shamn","0192","","","58.9333","17.8","4"],"148 70":["SE","148 70","Sorunda","Stockholm","AB","Nyn\u00e4shamn","0192","","","58.9802","17.9374","1"],"148 71":["SE","148 71","Sorunda","Stockholm","AB","Nyn\u00e4shamn","0192","","","58.9802","17.9374","1"],"148 91":["SE","148 91","\u00d6smo","Stockholm","AB","Nyn\u00e4shamn","0192","","","58.9833","17.9","4"],"148 92":["SE","148 92","\u00d6smo","Stockholm","AB","Nyn\u00e4shamn","0192","","","58.9833","17.9","4"],"148 96":["SE","148 96","Sorunda","Stockholm","AB","Nyn\u00e4shamn","0192","","","58.9832","17.9777","1"],"148 97":["SE","148 97","Sorunda","Stockholm","AB","Nyn\u00e4shamn","0192","","","58.9832","17.9777","1"],"149 00":["SE","149 00","Nyn\u00e4shamn","Stockholm","AB","Nyn\u00e4shamn","0192","","","58.9034","17.9479","4"],"149 02":["SE","149 02","Nyn\u00e4shamn","Stockholm","AB","Nyn\u00e4shamn","0192","","","58.9034","17.9479","4"],"149 21":["SE","149 21","Nyn\u00e4shamn","Stockholm","AB","Nyn\u00e4shamn","0192","","","58.9034","17.9479","4"],"149 22":["SE","149 22","Nyn\u00e4shamn","Stockholm","AB","Nyn\u00e4shamn","0192","","","58.9034","17.9479","4"],"149 23":["SE","149 23","Nyn\u00e4shamn","Stockholm","AB","Nyn\u00e4shamn","0192","","","58.9034","17.9479","4"],"149 25":["SE","149 25","Nyn\u00e4shamn","Stockholm","AB","Nyn\u00e4shamn","0192","","","58.9034","17.9479","4"],"149 30":["SE","149 30","Nyn\u00e4shamn","Stockholm","AB","Nyn\u00e4shamn","0192","","","58.9034","17.9479","4"],"149 31":["SE","149 31","Nyn\u00e4shamn","Stockholm","AB","Nyn\u00e4shamn","0192","","","58.9034","17.9479","4"],"149 32":["SE","149 32","Nyn\u00e4shamn","Stockholm","AB","Nyn\u00e4shamn","0192","","","58.9034","17.9479","4"],"149 33":["SE","149 33","Nyn\u00e4shamn","Stockholm","AB","Nyn\u00e4shamn","0192","","","58.9034","17.9479","4"],"149 34":["SE","149 34","Nyn\u00e4shamn","Stockholm","AB","Nyn\u00e4shamn","0192","","","58.9034","17.9479","4"],"149 35":["SE","149 35","Nyn\u00e4shamn","Stockholm","AB","Nyn\u00e4shamn","0192","","","58.9034","17.9479","4"],"149 40":["SE","149 40","Nyn\u00e4shamn","Stockholm","AB","Nyn\u00e4shamn","0192","","","58.9034","17.9479","4"],"149 41":["SE","149 41","Nyn\u00e4shamn","Stockholm","AB","Nyn\u00e4shamn","0192","","","58.9034","17.9479","4"],"149 43":["SE","149 43","Nyn\u00e4shamn","Stockholm","AB","Nyn\u00e4shamn","0192","","","58.9034","17.9479","4"],"149 45":["SE","149 45","Nyn\u00e4shamn","Stockholm","AB","Nyn\u00e4shamn","0192","","","58.9034","17.9479","4"],"149 50":["SE","149 50","Nyn\u00e4shamn","Stockholm","AB","Nyn\u00e4shamn","0192","","","58.9034","17.9479","4"],"149 51":["SE","149 51","Nyn\u00e4shamn","Stockholm","AB","Nyn\u00e4shamn","0192","","","58.9034","17.9479","4"],"149 80":["SE","149 80","Nyn\u00e4shamn","Stockholm","AB","Nyn\u00e4shamn","0192","","","58.9034","17.9479","4"],"149 81":["SE","149 81","Nyn\u00e4shamn","Stockholm","AB","Nyn\u00e4shamn","0192","","","58.9034","17.9479","4"],"149 82":["SE","149 82","Nyn\u00e4shamn","Stockholm","AB","Nyn\u00e4shamn","0192","","","58.9034","17.9479","4"],"149 91":["SE","149 91","Nyn\u00e4shamn","Stockholm","AB","Nyn\u00e4shamn","0192","","","58.9034","17.9479","4"],"149 92":["SE","149 92","Nyn\u00e4shamn","Stockholm","AB","Nyn\u00e4shamn","0192","","","58.9034","17.9479","4"],"149 95":["SE","149 95","Nyn\u00e4shamn","Stockholm","AB","Nyn\u00e4shamn","0192","","","58.9034","17.9479","4"],"141 20":["SE","141 20","Huddinge","Stockholm","AB","","","","","59.237","17.9819","4"],"142 20":["SE","142 20","Skog\u00e5s","Stockholm","AB","","","","","59.2167","18.15","4"],"143 20":["SE","143 20","V\u00e5rby","Stockholm","AB","","","","","59.2667","17.8833","4"],"144 20":["SE","144 20","R\u00f6nninge","Stockholm","AB","","","","","59.2","17.7333","4"],"144 52":["SE","144 52","R\u00f6nninge","Stockholm","AB","","","","","59.2","17.7333","4"],"145 20":["SE","145 20","Norsborg","Stockholm","AB","","","","","59.25","17.7833","4"],"146 20":["SE","146 20","Tullinge","Stockholm","AB","","","","","59.2","17.8833","4"],"147 20":["SE","147 20","Tumba","Stockholm","AB","","","","","59.1986","17.8332","4"],"147 45":["SE","147 45","Tumba","Stockholm","AB","","","","","59.1986","17.8332","4"],"148 20":["SE","148 20","\u00d6smo","Stockholm","AB","","","","","58.9833","17.9","4"],"149 20":["SE","149 20","Nyn\u00e4shamn","Stockholm","AB","","","","","58.9034","17.9479","4"],"148 40":["SE","148 40","Segers\u00e4ng","","","","","","","58.9802","17.9374","1"]}